duckflow/__init__.py
duckflow/core/__init__.py
duckflow/core/duck.py
duckflow/core/flock.py
duckflow/core/registry.py
duckflow/core/runner.py
duckflow/core/settings.py
duckflow/handlers/__init__.py
duckflow/handlers/duckduckgo_research.py
duckflow/handlers/openai_chat.py
duckflow/handlers/quack.py
duckflow/handlers/template.py
duckflow-0.1.2.dist-info/licenses/LICENSE
duckflow-0.1.2.dist-info/METADATA
duckflow-0.1.2.dist-info/WHEEL
duckflow-0.1.2.dist-info/entry_points.txt
duckflow-0.1.2.dist-info/top_level.txt
duckflow-0.1.2.dist-info/RECORD
