Metadata-Version: 2.4
Name: duckflow
Version: 0.1.2
Summary: 🦆 Have your ducks in a row, and watch them go. A playful pipeline framework for chaining AI and logic tasks.
Author-email: Mark Conde <markkristofferconde@gmail.com>
License: MIT
Project-URL: Homepage, https://github.com/markconde/duckflow
Project-URL: Source, https://github.com/markconde/duckflow
Project-URL: Issues, https://github.com/markconde/duckflow/issues
Classifier: Development Status :: 3 - Alpha
Classifier: Programming Language :: Python :: 3
Classifier: Programming Language :: Python :: 3.9
Classifier: Programming Language :: Python :: 3.10
Classifier: Programming Language :: Python :: 3.11
Classifier: License :: OSI Approved :: MIT License
Classifier: Operating System :: OS Independent
Requires-Python: >=3.9
License-File: LICENSE
Requires-Dist: openai>=1.0.0
Requires-Dist: requests>=2.28.0
Requires-Dist: python-dotenv>=1.0.0
Dynamic: license-file
